{"frames": {

"icon":
{
	"frame": {"x":526,"y":668,"w":100,"h":100},
	"rotated": false,
	"trimmed": false,
	"spriteSourceSize": {"x":0,"y":0,"w":100,"h":100},
	"sourceSize": {"w":100,"h":100}
},
"panel":
{
	"frame": {"x":268,"y":604,"w":257,"h":90},
	"rotated": false,
	"trimmed": false,
	"spriteSourceSize": {"x":0,"y":0,"w":257,"h":90},
	"sourceSize": {"w":257,"h":90}
},
"percent":
{
	"frame": {"x":1,"y":604,"w":266,"h":90},
	"rotated": false,
	"trimmed": false,
	"spriteSourceSize": {"x":0,"y":0,"w":266,"h":90},
	"sourceSize": {"w":266,"h":90}
},
"timer":
{
	"frame": {"x":526,"y":604,"w":178,"h":63},
	"rotated": false,
	"trimmed": false,
	"spriteSourceSize": {"x":0,"y":0,"w":178,"h":63},
	"sourceSize": {"w":178,"h":63}
},
"window_back":
{
	"frame": {"x":1,"y":1,"w":662,"h":602},
	"rotated": false,
	"trimmed": false,
	"spriteSourceSize": {"x":0,"y":0,"w":662,"h":602},
	"sourceSize": {"w":662,"h":602}
}},
"meta": {
	"app": "Adobe Animate",
	"version": "18.0.0.107",
	"image": "sale_magnet_pack.png",
	"format": "RGBA8888",
	"size": {"w":1024,"h":1024},
	"scale": "1"
}
}
